[
    {
        "tradeDate": "2023-12-20",
        "tradeTime": "1600",
        "tradeType": "BUY",
        "tradeSize": "10",
        "symbol": "META",
        "tradeCond": "atLimit",
        "tradePrice": "350.04",
        "rawtradeId": "194",
        "tradeCnt": "7",
        "tradeAboveBelow": "above",
        "tradePivot": "S1",
        "priceDist": "4.22",
        "pricePct": "1.2046%",
        "tradeStrong": "0",
        "tradeLeg": "1",
        "timestamp": "2024-01-14T042547"
    },
    {
        "tradeDate": "2023-12-20",
        "tradeTime": "1600",
        "tradeType": "BUY",
        "tradeSize": "10",
        "symbol": "GLD",
        "tradeCond": "atLimit",
        "tradePrice": "188.4",
        "rawtradeId": "199",
        "tradeCnt": "4",
        "tradeAboveBelow": "above",
        "tradePivot": "S1",
        "priceDist": "0.15",
        "pricePct": "0.0778%",
        "tradeStrong": "0",
        "tradeLeg": "1",
        "timestamp": "2024-01-14T042547"
    },
    {
        "tradeDate": "2023-12-20",
        "tradeTime": "1500",
        "tradeType": "SELL",
        "tradeSize": "10",
        "symbol": "GLD",
        "tradeCond": "atLimit",
        "tradePrice": "188.73",
        "rawtradeId": "198",
        "tradeCnt": "7",
        "tradeAboveBelow": "below",
        "tradePivot": "R1",
        "priceDist": "-1.12",
        "pricePct": "-0.5923%",
        "tradeStrong": "0",
        "tradeLeg": "1",
        "timestamp": "2024-01-14T042547"
    },
    {
        "tradeDate": "2023-12-20",
        "tradeTime": "1445",
        "tradeType": "SELL",
        "tradeSize": "10",
        "symbol": "ROKU",
        "tradeCond": "atLimit",
        "tradePrice": "92.62",
        "rawtradeId": "193",
        "tradeCnt": "5",
        "tradeAboveBelow": "below",
        "tradePivot": "R1",
        "priceDist": "-3.33",
        "pricePct": "-3.5953%",
        "tradeStrong": "0",
        "tradeLeg": "1",
        "timestamp": "2024-01-14T042547"
    },
    {
        "tradeDate": "2023-12-20",
        "tradeTime": "1445",
        "tradeType": "SELL",
        "tradeSize": "10",
        "symbol": "ROKU",
        "tradeCond": "atLimit",
        "tradePrice": "92.62",
        "rawtradeId": "204",
        "tradeCnt": "5",
        "tradeAboveBelow": "below",
        "tradePivot": "R1",
        "priceDist": "-3.33",
        "pricePct": "-3.5953%",
        "tradeStrong": "0",
        "tradeLeg": "1",
        "timestamp": "2024-01-14T042547"
    },
    {
        "tradeDate": "2023-12-20",
        "tradeTime": "1430",
        "tradeType": "SELL",
        "tradeSize": "10",
        "symbol": "TSLA",
        "tradeCond": "atLimit",
        "tradePrice": "256.87",
        "rawtradeId": "192",
        "tradeCnt": "5",
        "tradeAboveBelow": "below",
        "tradePivot": "R1",
        "priceDist": "-2.49",
        "pricePct": "-0.9689%",
        "tradeStrong": "0",
        "tradeLeg": "1",
        "timestamp": "2024-01-14T042547"
    },
    {
        "tradeDate": "2023-12-20",
        "tradeTime": "1415",
        "tradeType": "SELL",
        "tradeSize": "10",
        "symbol": "META",
        "tradeCond": "atLimit",
        "tradePrice": "352.98",
        "rawtradeId": "190",
        "tradeCnt": "4",
        "tradeAboveBelow": "below",
        "tradePivot": "R1",
        "priceDist": "-1.32",
        "pricePct": "-0.3740%",
        "tradeStrong": "0",
        "tradeLeg": "1",
        "timestamp": "2024-01-14T042547"
    },
    {
        "tradeDate": "2023-12-20",
        "tradeTime": "1415",
        "tradeType": "SELL",
        "tradeSize": "10",
        "symbol": "AMZN",
        "tradeCond": "atLimit",
        "tradePrice": "155.11",
        "rawtradeId": "191",
        "tradeCnt": "5",
        "tradeAboveBelow": "above",
        "tradePivot": "R1",
        "priceDist": "0.08",
        "pricePct": "0.0494%",
        "tradeStrong": "1",
        "tradeLeg": "1",
        "timestamp": "2024-01-14T042547"
    },
    {
        "tradeDate": "2023-12-20",
        "tradeTime": "1400",
        "tradeType": "BUY",
        "tradeSize": "10",
        "symbol": "INTC",
        "tradeCond": "atLimit",
        "tradePrice": "46.6",
        "rawtradeId": "189",
        "tradeCnt": "6",
        "tradeAboveBelow": "above",
        "tradePivot": "S1",
        "priceDist": "0.71",
        "pricePct": "1.5165%",
        "tradeStrong": "0",
        "tradeLeg": "1",
        "timestamp": "2024-01-14T042547"
    },
    {
        "tradeDate": "2023-12-20",
        "tradeTime": "1400",
        "tradeType": "SELL",
        "tradeSize": "10",
        "symbol": "NFLX",
        "tradeCond": "atLimit",
        "tradePrice": "500.21",
        "rawtradeId": "201",
        "tradeCnt": "8",
        "tradeAboveBelow": "above",
        "tradePivot": "R1",
        "priceDist": "0.76",
        "pricePct": "0.1515%",
        "tradeStrong": "1",
        "tradeLeg": "1",
        "timestamp": "2024-01-14T042547"
    },
    {
        "tradeDate": "2023-12-20",
        "tradeTime": "1345",
        "tradeType": "SELL",
        "tradeSize": "10",
        "symbol": "SPY",
        "tradeCond": "atLimit",
        "tradePrice": "475.61",
        "rawtradeId": "188",
        "tradeCnt": "5",
        "tradeAboveBelow": "below",
        "tradePivot": "R1",
        "priceDist": "-0.07",
        "pricePct": "-0.0147%",
        "tradeStrong": "0",
        "tradeLeg": "1",
        "timestamp": "2024-01-14T042547"
    },
    {
        "tradeDate": "2023-12-20",
        "tradeTime": "1330",
        "tradeType": "SELL",
        "tradeSize": "10",
        "symbol": "GS",
        "tradeCond": "atLimit",
        "tradePrice": "384.75",
        "rawtradeId": "187",
        "tradeCnt": "4",
        "tradeAboveBelow": "below",
        "tradePivot": "R1",
        "priceDist": "-1.31",
        "pricePct": "-0.3396%",
        "tradeStrong": "0",
        "tradeLeg": "1",
        "timestamp": "2024-01-14T042547"
    },
    {
        "tradeDate": "2023-12-20",
        "tradeTime": "1315",
        "tradeType": "BUY",
        "tradeSize": "10",
        "symbol": "NVDA",
        "tradeCond": "atLimit",
        "tradePrice": "497.89",
        "rawtradeId": "170",
        "tradeCnt": "5",
        "tradeAboveBelow": "above",
        "tradePivot": "S1",
        "priceDist": "6.84",
        "pricePct": "1.3731%",
        "tradeStrong": "0",
        "tradeLeg": "1",
        "timestamp": "2024-01-14T042547"
    },
    {
        "tradeDate": "2023-12-20",
        "tradeTime": "1315",
        "tradeType": "BUY",
        "tradeSize": "10",
        "symbol": "TSLA",
        "tradeCond": "atLimit",
        "tradePrice": "256.17",
        "rawtradeId": "180",
        "tradeCnt": "9",
        "tradeAboveBelow": "above",
        "tradePivot": "S1",
        "priceDist": "2.15",
        "pricePct": "0.8380%",
        "tradeStrong": "0",
        "tradeLeg": "1",
        "timestamp": "2024-01-14T042547"
    },
    {
        "tradeDate": "2023-12-20",
        "tradeTime": "1315",
        "tradeType": "BUY",
        "tradeSize": "10",
        "symbol": "META",
        "tradeCond": "atLimit",
        "tradePrice": "352.64",
        "rawtradeId": "182",
        "tradeCnt": "8",
        "tradeAboveBelow": "above",
        "tradePivot": "S1",
        "priceDist": "6.82",
        "pricePct": "1.9331%",
        "tradeStrong": "0",
        "tradeLeg": "1",
        "timestamp": "2024-01-14T042547"
    },
    {
        "tradeDate": "2023-12-20",
        "tradeTime": "1315",
        "tradeType": "SELL",
        "tradeSize": "10",
        "symbol": "ROKU",
        "tradeCond": "atLimit",
        "tradePrice": "92.32",
        "rawtradeId": "186",
        "tradeCnt": "4",
        "tradeAboveBelow": "below",
        "tradePivot": "R1",
        "priceDist": "-3.63",
        "pricePct": "-3.9270%",
        "tradeStrong": "0",
        "tradeLeg": "1",
        "timestamp": "2024-01-14T042547"
    },
    {
        "tradeDate": "2023-12-20",
        "tradeTime": "1315",
        "tradeType": "SELL",
        "tradeSize": "10",
        "symbol": "ROKU",
        "tradeCond": "atLimit",
        "tradePrice": "92.32",
        "rawtradeId": "203",
        "tradeCnt": "4",
        "tradeAboveBelow": "below",
        "tradePivot": "R1",
        "priceDist": "-3.63",
        "pricePct": "-3.9270%",
        "tradeStrong": "0",
        "tradeLeg": "1",
        "timestamp": "2024-01-14T042547"
    },
    {
        "tradeDate": "2023-12-20",
        "tradeTime": "1300",
        "tradeType": "BUY",
        "tradeSize": "10",
        "symbol": "AMZN",
        "tradeCond": "atLimit",
        "tradePrice": "154.51",
        "rawtradeId": "172",
        "tradeCnt": "7",
        "tradeAboveBelow": "above",
        "tradePivot": "S1",
        "priceDist": "1.91",
        "pricePct": "1.2340%",
        "tradeStrong": "0",
        "tradeLeg": "1",
        "timestamp": "2024-01-14T042547"
    },
    {
        "tradeDate": "2023-12-20",
        "tradeTime": "1300",
        "tradeType": "BUY",
        "tradeSize": "10",
        "symbol": "HBAN",
        "tradeCond": "atLimit",
        "tradePrice": "12.84",
        "rawtradeId": "184",
        "tradeCnt": "4",
        "tradeAboveBelow": "above",
        "tradePivot": "S1",
        "priceDist": "0.19",
        "pricePct": "1.4801%",
        "tradeStrong": "0",
        "tradeLeg": "1",
        "timestamp": "2024-01-14T042547"
    },
    {
        "tradeDate": "2023-12-20",
        "tradeTime": "1245",
        "tradeType": "SELL",
        "tradeSize": "10",
        "symbol": "GLD",
        "tradeCond": "atLimit",
        "tradePrice": "188.55",
        "rawtradeId": "197",
        "tradeCnt": "5",
        "tradeAboveBelow": "below",
        "tradePivot": "R1",
        "priceDist": "-1.29",
        "pricePct": "-0.6859%",
        "tradeStrong": "0",
        "tradeLeg": "1",
        "timestamp": "2024-01-14T042547"
    },
    {
        "tradeDate": "2023-12-20",
        "tradeTime": "1230",
        "tradeType": "BUY",
        "tradeSize": "10",
        "symbol": "SPY",
        "tradeCond": "atLimit",
        "tradePrice": "475.35",
        "rawtradeId": "174",
        "tradeCnt": "4",
        "tradeAboveBelow": "above",
        "tradePivot": "S1",
        "priceDist": "2.15",
        "pricePct": "0.4516%",
        "tradeStrong": "0",
        "tradeLeg": "1",
        "timestamp": "2024-01-14T042547"
    },
    {
        "tradeDate": "2023-12-20",
        "tradeTime": "1215",
        "tradeType": "SELL",
        "tradeSize": "10",
        "symbol": "GS",
        "tradeCond": "atLimit",
        "tradePrice": "383.43",
        "rawtradeId": "176",
        "tradeCnt": "7",
        "tradeAboveBelow": "below",
        "tradePivot": "R1",
        "priceDist": "-2.63",
        "pricePct": "-0.6848%",
        "tradeStrong": "0",
        "tradeLeg": "1",
        "timestamp": "2024-01-14T042547"
    },
    {
        "tradeDate": "2023-12-20",
        "tradeTime": "1215",
        "tradeType": "BUY",
        "tradeSize": "10",
        "symbol": "ROKU",
        "tradeCond": "atLimit",
        "tradePrice": "91.84",
        "rawtradeId": "185",
        "tradeCnt": "14",
        "tradeAboveBelow": "below",
        "tradePivot": "S1",
        "priceDist": "-1.48",
        "pricePct": "-1.6115%",
        "tradeStrong": "1",
        "tradeLeg": "1",
        "timestamp": "2024-01-14T042547"
    },
    {
        "tradeDate": "2023-12-20",
        "tradeTime": "1215",
        "tradeType": "BUY",
        "tradeSize": "10",
        "symbol": "ROKU",
        "tradeCond": "atLimit",
        "tradePrice": "91.84",
        "rawtradeId": "202",
        "tradeCnt": "14",
        "tradeAboveBelow": "below",
        "tradePivot": "S1",
        "priceDist": "-1.48",
        "pricePct": "-1.6115%",
        "tradeStrong": "1",
        "tradeLeg": "1",
        "timestamp": "2024-01-14T042547"
    },
    {
        "tradeDate": "2023-12-20",
        "tradeTime": "1200",
        "tradeType": "SELL",
        "tradeSize": "10",
        "symbol": "AAPL",
        "tradeCond": "atLimit",
        "tradePrice": "197.38",
        "rawtradeId": "175",
        "tradeCnt": "5",
        "tradeAboveBelow": "above",
        "tradePivot": "R1",
        "priceDist": "0.09",
        "pricePct": "0.0462%",
        "tradeStrong": "1",
        "tradeLeg": "1",
        "timestamp": "2024-01-14T042547"
    },
    {
        "tradeDate": "2023-12-20",
        "tradeTime": "1200",
        "tradeType": "SELL",
        "tradeSize": "10",
        "symbol": "HBAN",
        "tradeCond": "atLimit",
        "tradePrice": "12.84",
        "rawtradeId": "183",
        "tradeCnt": "4",
        "tradeAboveBelow": "below",
        "tradePivot": "R1",
        "priceDist": "-0.02",
        "pricePct": "-0.1817%",
        "tradeStrong": "0",
        "tradeLeg": "1",
        "timestamp": "2024-01-14T042547"
    },
    {
        "tradeDate": "2023-12-20",
        "tradeTime": "1145",
        "tradeType": "SELL",
        "tradeSize": "10",
        "symbol": "INTC",
        "tradeCond": "atLimit",
        "tradePrice": "46.78",
        "rawtradeId": "177",
        "tradeCnt": "4",
        "tradeAboveBelow": "below",
        "tradePivot": "R1",
        "priceDist": "-0.28",
        "pricePct": "-0.5961%",
        "tradeStrong": "0",
        "tradeLeg": "1",
        "timestamp": "2024-01-14T042547"
    },
    {
        "tradeDate": "2023-12-20",
        "tradeTime": "1130",
        "tradeType": "SELL",
        "tradeSize": "10",
        "symbol": "SPY",
        "tradeCond": "atLimit",
        "tradePrice": "475.3",
        "rawtradeId": "173",
        "tradeCnt": "5",
        "tradeAboveBelow": "below",
        "tradePivot": "R1",
        "priceDist": "-0.38",
        "pricePct": "-0.0800%",
        "tradeStrong": "0",
        "tradeLeg": "1",
        "timestamp": "2024-01-14T042547"
    },
    {
        "tradeDate": "2023-12-20",
        "tradeTime": "1130",
        "tradeType": "SELL",
        "tradeSize": "10",
        "symbol": "QQQ",
        "tradeCond": "atLimit",
        "tradePrice": "409.99",
        "rawtradeId": "178",
        "tradeCnt": "5",
        "tradeAboveBelow": "above",
        "tradePivot": "R1",
        "priceDist": "0.15",
        "pricePct": "0.0355%",
        "tradeStrong": "1",
        "tradeLeg": "1",
        "timestamp": "2024-01-14T042547"
    },
    {
        "tradeDate": "2023-12-20",
        "tradeTime": "1130",
        "tradeType": "BUY",
        "tradeSize": "10",
        "symbol": "GLD",
        "tradeCond": "atLimit",
        "tradePrice": "188.52",
        "rawtradeId": "196",
        "tradeCnt": "6",
        "tradeAboveBelow": "above",
        "tradePivot": "S1",
        "priceDist": "0.27",
        "pricePct": "0.1432%",
        "tradeStrong": "0",
        "tradeLeg": "1",
        "timestamp": "2024-01-14T042547"
    },
    {
        "tradeDate": "2023-12-20",
        "tradeTime": "1130",
        "tradeType": "SELL",
        "tradeSize": "10",
        "symbol": "NFLX",
        "tradeCond": "atLimit",
        "tradePrice": "498.31",
        "rawtradeId": "200",
        "tradeCnt": "7",
        "tradeAboveBelow": "below",
        "tradePivot": "R1",
        "priceDist": "-1.14",
        "pricePct": "-0.2285%",
        "tradeStrong": "0",
        "tradeLeg": "1",
        "timestamp": "2024-01-14T042547"
    },
    {
        "tradeDate": "2023-12-20",
        "tradeTime": "1115",
        "tradeType": "SELL",
        "tradeSize": "10",
        "symbol": "AMZN",
        "tradeCond": "atLimit",
        "tradePrice": "155.15",
        "rawtradeId": "171",
        "tradeCnt": "6",
        "tradeAboveBelow": "above",
        "tradePivot": "R1",
        "priceDist": "0.12",
        "pricePct": "0.0745%",
        "tradeStrong": "1",
        "tradeLeg": "1",
        "timestamp": "2024-01-14T042547"
    },
    {
        "tradeDate": "2023-12-20",
        "tradeTime": "1115",
        "tradeType": "SELL",
        "tradeSize": "10",
        "symbol": "META",
        "tradeCond": "atLimit",
        "tradePrice": "353.68",
        "rawtradeId": "181",
        "tradeCnt": "4",
        "tradeAboveBelow": "below",
        "tradePivot": "R1",
        "priceDist": "-0.62",
        "pricePct": "-0.1753%",
        "tradeStrong": "0",
        "tradeLeg": "1",
        "timestamp": "2024-01-14T042547"
    },
    {
        "tradeDate": "2023-12-20",
        "tradeTime": "1100",
        "tradeType": "SELL",
        "tradeSize": "10",
        "symbol": "NVDA",
        "tradeCond": "atLimit",
        "tradePrice": "498.08",
        "rawtradeId": "169",
        "tradeCnt": "5",
        "tradeAboveBelow": "below",
        "tradePivot": "R1",
        "priceDist": "-1.02",
        "pricePct": "-0.2055%",
        "tradeStrong": "0",
        "tradeLeg": "1",
        "timestamp": "2024-01-14T042547"
    },
    {
        "tradeDate": "2023-12-20",
        "tradeTime": "1100",
        "tradeType": "SELL",
        "tradeSize": "10",
        "symbol": "TSLA",
        "tradeCond": "atLimit",
        "tradePrice": "258.71",
        "rawtradeId": "179",
        "tradeCnt": "5",
        "tradeAboveBelow": "below",
        "tradePivot": "R1",
        "priceDist": "-0.64",
        "pricePct": "-0.2482%",
        "tradeStrong": "0",
        "tradeLeg": "1",
        "timestamp": "2024-01-14T042547"
    },
    {
        "tradeDate": "2023-12-20",
        "tradeTime": "1045",
        "tradeType": "SELL",
        "tradeSize": "10",
        "symbol": "XOM",
        "tradeCond": "atLimit",
        "tradePrice": "103.32",
        "rawtradeId": "195",
        "tradeCnt": "4",
        "tradeAboveBelow": "below",
        "tradePivot": "R1",
        "priceDist": "-0.19",
        "pricePct": "-0.1796%",
        "tradeStrong": "0",
        "tradeLeg": "1",
        "timestamp": "2024-01-14T042547"
    }
]